sdkms_cli/VERSION
sdkms_cli/__init__.py
sdkms_cli/__main__.py
sdkms_cli/pycompatible.py
sdkms_cli-5.4.2891.dist-info/METADATA
sdkms_cli-5.4.2891.dist-info/WHEEL
sdkms_cli-5.4.2891.dist-info/entry_points.txt
sdkms_cli-5.4.2891.dist-info/top_level.txt
sdkms_cli-5.4.2891.dist-info/RECORD
