Metadata-Version: 2.1
Name: sdkms-cli
Version: 5.4.2891
Summary: Fortanix SDKMS CLI
Home-page: https://support.fortanix.com
Author: Fortanix
Author-email: support@fortanix.com
License: Apache 2.0
Keywords: CLI,Fortanix SDKMS
Classifier: Development Status :: 5 - Production/Stable
Classifier: Intended Audience :: Developers
Classifier: Intended Audience :: System Administrators
Classifier: License :: OSI Approved :: Apache Software License
Classifier: Programming Language :: Python :: 3
Classifier: Topic :: Security :: Cryptography
Requires-Dist: argparse >=1.4.0
Requires-Dist: certifi >=2022.5.18.1
Requires-Dist: cryptography >=37.0
Requires-Dist: enum34 >=1.1.2
Requires-Dist: requests >=2.27.1
Requires-Dist: sdkms ==5.4.2891
Requires-Dist: six >=1.15.0
